{
  "nodes": [
    {
      "id": 0,
      "address": "0x3952569ecdaf0cb58d8bf174a1d495e8",
      "name": "Ida",
      "group": 2,
      "subjectiveProbs": {
        "p": 0.33152187799670013,
        "q": 0.21516687235101167,
        "r": 0.4533112496522882
      },
      "evidence": {
        "e1": 0.32598782927722325,
        "e2": 0.4016724964498545,
        "e3": 0.27233967427292227
      },
      "trustMetrics": {
        "directTrust": 0.8945968420904631,
        "indirectTrust": 0.8471578827043554,
        "overallTrust": 0.04354386811987047
      },
      "isSybil": true
    },
    {
      "id": 1,
      "address": "0xbe8076f90f3fc2c403e53bc75f60f27f",
      "name": "Jack",
      "group": 5,
      "subjectiveProbs": {
        "p": 0.3658478815310698,
        "q": 0.2824459578305122,
        "r": 0.35170616063841803
      },
      "evidence": {
        "e1": 0.397404521592525,
        "e2": 0.4017292107227711,
        "e3": 0.20086626768470392
      },
      "trustMetrics": {
        "directTrust": 0.20447073548985284,
        "indirectTrust": 0.8644110353693707,
        "overallTrust": 0.02672204427148059
      },
      "isSybil": true
    },
    {
      "id": 2,
      "address": "0xd376345e237d74706d0f47fff0d66ce9",
      "name": "Dave",
      "group": 4,
      "subjectiveProbs": {
        "p": 0.4486364778222453,
        "q": 0.34636776270158376,
        "r": 0.20499575947617094
      },
      "evidence": {
        "e1": 0.4968649168359388,
        "e2": 0.28336239032556887,
        "e3": 0.21977269283849235
      },
      "trustMetrics": {
        "directTrust": 1.0148456521387177,
        "indirectTrust": 0.844151662453149,
        "overallTrust": 0.04647493286479667
      },
      "isSybil": true
    },
    {
      "id": 3,
      "address": "0x8a11057374678a238b7ba32eb3d78a96",
      "name": "Charlie",
      "group": 6,
      "subjectiveProbs": {
        "p": 0.2387578887474319,
        "q": 0.7086495392953536,
        "r": 0.05259257195721449
      },
      "evidence": {
        "e1": 0.0899411450989648,
        "e2": 0.5069712526563569,
        "e3": 0.4030876022446783
      },
      "trustMetrics": {
        "directTrust": 0.692848493864657,
        "indirectTrust": 0.8522015914100006,
        "overallTrust": 0.03862625213186644
      },
      "isSybil": true
    },
    {
      "id": 4,
      "address": "0xb690ab6f7eaf24a1ed24bce5ef94d503",
      "name": "Alice",
      "group": 4,
      "subjectiveProbs": {
        "p": 0.4006615346300169,
        "q": 0.2130975698629913,
        "r": 0.3862408955069918
      },
      "evidence": {
        "e1": 0.4028361656454,
        "e2": 0.32901526098160433,
        "e3": 0.2681485733729957
      },
      "trustMetrics": {
        "directTrust": 0.9648370795192613,
        "indirectTrust": 0.8454018767686355,
        "overallTrust": 0.04525597390719742
      },
      "isSybil": true
    },
    {
      "id": 5,
      "address": "0xeb1a7cb8d343b10e9d65c7568eddd472",
      "name": "Dave",
      "group": 4,
      "subjectiveProbs": {
        "p": 0.029577346490047954,
        "q": 0.6872171979951837,
        "r": 0.2832054555147684
      },
      "evidence": {
        "e1": 0.3809848003151682,
        "e2": 0.3803455462447466,
        "e3": 0.23866965344008528
      },
      "trustMetrics": {
        "directTrust": 0.9734139743187902,
        "indirectTrust": 0.8451874543986472,
        "overallTrust": 0.045465035717935934
      },
      "isSybil": true
    },
    {
      "id": 6,
      "address": "0x2144a312e0c8a33e4577773a35d9978f",
      "name": "Ida",
      "group": 3,
      "subjectiveProbs": {
        "p": 0.5163349782463322,
        "q": 0.28937971617120917,
        "r": 0.19428530558245857
      },
      "evidence": {
        "e1": 0.5160994956569956,
        "e2": 0.12238872778731957,
        "e3": 0.36151177655568484
      },
      "trustMetrics": {
        "directTrust": 0.2161014960782019,
        "indirectTrust": 0.864120266354662,
        "overallTrust": 0.027005544060821597
      },
      "isSybil": true
    },
    {
      "id": 7,
      "address": "0x4ef3005c86059f64fd7c73b96334d64a",
      "name": "Bob",
      "group": 4,
      "subjectiveProbs": {
        "p": 0.3081921021726944,
        "q": 0.07422109706181679,
        "r": 0.6175868007654888
      },
      "evidence": {
        "e1": 0.08489425332413483,
        "e2": 0.6087616244756455,
        "e3": 0.30634412220021967
      },
      "trustMetrics": {
        "directTrust": 0.8274075696852351,
        "indirectTrust": 0.848837614514486,
        "overallTrust": 0.04190612960499303
      },
      "isSybil": true
    },
    {
      "id": 8,
      "address": "0xc04487b5b84c453247f9e4a4f90ae64a",
      "name": "Jack",
      "group": 5,
      "subjectiveProbs": {
        "p": 0.5090536950793713,
        "q": 0.007817854787055016,
        "r": 0.4831284501335737
      },
      "evidence": {
        "e1": 0.330745653909011,
        "e2": 0.4524781102602976,
        "e3": 0.21677623583069147
      },
      "trustMetrics": {
        "directTrust": 0.1827932799879312,
        "indirectTrust": 0.8649529717569188,
        "overallTrust": 0.026193656293621248
      },
      "isSybil": true
    },
    {
      "id": 9,
      "address": "0xb18f8cbc139191d067ffc7e9760a23fa",
      "name": "Dave",
      "group": 3,
      "subjectiveProbs": {
        "p": 0.33704246589283937,
        "q": 0.5350543322096118,
        "r": 0.1279032018975488
      },
      "evidence": {
        "e1": 0.18571560923540575,
        "e2": 0.4704126432011041,
        "e3": 0.34387174756349015
      },
      "trustMetrics": {
        "directTrust": 0.2113531510122418,
        "indirectTrust": 0.8642389749813109,
        "overallTrust": 0.026889803149838815
      },
      "isSybil": true
    },
    {
      "id": 10,
      "address": "0x246e85800c86ab439197f4492f212053",
      "name": "Dave",
      "group": 5,
      "subjectiveProbs": {
        "p": 0.41900273020094764,
        "q": 0.3216358351261471,
        "r": 0.2593614346729054
      },
      "evidence": {
        "e1": 0.4581968911225476,
        "e2": 0.48650989552728624,
        "e3": 0.055293213350166195
      },
      "trustMetrics": {
        "directTrust": 0.21682136793598414,
        "indirectTrust": 0.8641022695582175,
        "overallTrust": 0.027023090937355037
      },
      "isSybil": true
    },
    {
      "id": 11,
      "address": "0x614b6cb1a6d460a95efdce42234d20e4",
      "name": "Alice",
      "group": 4,
      "subjectiveProbs": {
        "p": 0.5397248352325724,
        "q": 0.20690290164592498,
        "r": 0.2533722631215026
      },
      "evidence": {
        "e1": 0.48424840692361454,
        "e2": 0.25499219403850937,
        "e3": 0.2607593990378761
      },
      "trustMetrics": {
        "directTrust": 1.0363362470236042,
        "indirectTrust": 0.843614397581027,
        "overallTrust": 0.046998766115115775
      },
      "isSybil": true
    },
    {
      "id": 12,
      "address": "0x7511cfa9a3e90363e06314cd65316a91",
      "name": "Jack",
      "group": 6,
      "subjectiveProbs": {
        "p": 0.08134361522509453,
        "q": 0.46481284896384134,
        "r": 0.4538435358110641
      },
      "evidence": {
        "e1": 0.4397294782492282,
        "e2": 0.16415316369487737,
        "e3": 0.39611735805589443
      },
      "trustMetrics": {
        "directTrust": 0.5689294423381658,
        "indirectTrust": 0.855299567698163,
        "overallTrust": 0.035605725250908216
      },
      "isSybil": true
    },
    {
      "id": 13,
      "address": "0xb56821fd0681dead38f013a2186cf50b",
      "name": "Dave",
      "group": 7,
      "subjectiveProbs": {
        "p": 0.21176809686747988,
        "q": 0.30799245748197607,
        "r": 0.48023944565054405
      },
      "evidence": {
        "e1": 0.094290599298636,
        "e2": 0.5329335524806974,
        "e3": 0.3727758482206666
      },
      "trustMetrics": {
        "directTrust": 0.2615272225074179,
        "indirectTrust": 0.8629846231939314,
        "overallTrust": 0.028112796142533737
      },
      "isSybil": true
    },
    {
      "id": 14,
      "address": "0xd1b30807957991c8d1523a2f40111585",
      "name": "Bob",
      "group": 2,
      "subjectiveProbs": {
        "p": 0.34750849699523134,
        "q": 0.27501304836558366,
        "r": 0.377478454639185
      },
      "evidence": {
        "e1": 0.28165478867126215,
        "e2": 0.43653613727881474,
        "e3": 0.2818090740499231
      },
      "trustMetrics": {
        "directTrust": 0.9048172395091956,
        "indirectTrust": 0.8469023727688871,
        "overallTrust": 0.043792990306952065
      },
      "isSybil": true
    },
    {
      "id": 15,
      "address": "0x885f816b2771e8097dff91f92593321d",
      "name": "Bob",
      "group": 0,
      "subjectiveProbs": {
        "p": 0.4375486800445208,
        "q": 0.4278819937707104,
        "r": 0.1345693261847688
      },
      "evidence": {
        "e1": 0.1486960327206991,
        "e2": 0.795083058124833,
        "e3": 0.05622090915446785
      },
      "trustMetrics": {
        "directTrust": 0.6545548189032647,
        "indirectTrust": 0.8531589332840352,
        "overallTrust": 0.0376928438046825
      },
      "isSybil": true
    },
    {
      "id": 16,
      "address": "0x19373b45f2d4d3dc70d1d975ce873e99",
      "name": "Frank",
      "group": 6,
      "subjectiveProbs": {
        "p": 0.27868975535233154,
        "q": 0.473437551778183,
        "r": 0.2478726928694855
      },
      "evidence": {
        "e1": 0.09673520213929909,
        "e2": 0.38421850624498655,
        "e3": 0.5190462916157144
      },
      "trustMetrics": {
        "directTrust": 0.6240451450735393,
        "indirectTrust": 0.8539216751297785,
        "overallTrust": 0.03694917050508294
      },
      "isSybil": true
    },
    {
      "id": 17,
      "address": "0x93e95a98360d347294a580f131734c0c",
      "name": "Henry",
      "group": 4,
      "subjectiveProbs": {
        "p": 0.0018581386645616297,
        "q": 0.6146733252777408,
        "r": 0.38346853605769754
      },
      "evidence": {
        "e1": 0.5380468600131806,
        "e2": 0.38429268948542844,
        "e3": 0.07766045050139096
      },
      "trustMetrics": {
        "directTrust": 0.8404028463305045,
        "indirectTrust": 0.8485127325983542,
        "overallTrust": 0.04222288947322147
      },
      "isSybil": true
    },
    {
      "id": 18,
      "address": "0x74d79fa1bdd7de0ecbf3faeaf89b9193",
      "name": "Gina",
      "group": 2,
      "subjectiveProbs": {
        "p": 0.6644852280425935,
        "q": 0.3237650552283067,
        "r": 0.011749716729099906
      },
      "evidence": {
        "e1": 0.16958821530423276,
        "e2": 0.3974940211048839,
        "e3": 0.43291776359088335
      },
      "trustMetrics": {
        "directTrust": 0.7667928488825576,
        "indirectTrust": 0.850352982534553,
        "overallTrust": 0.040428645785427764
      },
      "isSybil": true
    },
    {
      "id": 19,
      "address": "0xabe3d3444dc241c070d347d792c15e0d",
      "name": "Gina",
      "group": 0,
      "subjectiveProbs": {
        "p": 0.27810372609748213,
        "q": 0.47278820110465325,
        "r": 0.24910807279786457
      },
      "evidence": {
        "e1": 0.16563143412524559,
        "e2": 0.5022957188321657,
        "e3": 0.3320728470425887
      },
      "trustMetrics": {
        "directTrust": 0.6131100646054659,
        "indirectTrust": 0.8541950521414803,
        "overallTrust": 0.03668262791867365
      },
      "isSybil": true
    },
    {
      "id": 20,
      "address": "0x5f1275d73084ed613b181b28e8b39fb9",
      "name": "Frank",
      "group": 5,
      "subjectiveProbs": {
        "p": 0.06950889886894042,
        "q": 0.4540032256134317,
        "r": 0.4764878755176279
      },
      "evidence": {
        "e1": 0.2952748479621684,
        "e2": 0.27361139233746473,
        "e3": 0.43111375970036675
      },
      "trustMetrics": {
        "directTrust": 0.6040853834137682,
        "indirectTrust": 0.8544206691712727,
        "overallTrust": 0.03646265131462602
      },
      "isSybil": false
    },
    {
      "id": 21,
      "address": "0xa54d4f5599452acdce71d9e2c33fe87c",
      "name": "Frank",
      "group": 4,
      "subjectiveProbs": {
        "p": 0.1840907300255651,
        "q": 0.3409218701776735,
        "r": 0.4749873997967614
      },
      "evidence": {
        "e1": 0.3449818498314568,
        "e2": 0.2713657963356926,
        "e3": 0.38365235383285073
      },
      "trustMetrics": {
        "directTrust": 1.9525444198490005,
        "indirectTrust": 0.8207091932603919,
        "overallTrust": 0.06933134032773482
      },
      "isSybil": false
    },
    {
      "id": 22,
      "address": "0xcc9d17bca4b27563b9c6c1f633af0de0",
      "name": "Ida",
      "group": 3,
      "subjectiveProbs": {
        "p": 0.5582422463944917,
        "q": 0.09420792650095512,
        "r": 0.34754982710455323
      },
      "evidence": {
        "e1": 0.3943169288939292,
        "e2": 0.35731147263981466,
        "e3": 0.24837159846625614
      },
      "trustMetrics": {
        "directTrust": 0.4274546470904437,
        "indirectTrust": 0.8588364375793558,
        "overallTrust": 0.03215727711674499
      },
      "isSybil": false
    },
    {
      "id": 23,
      "address": "0xde1e3c3339fddb24f330423292c80923",
      "name": "Frank",
      "group": 2,
      "subjectiveProbs": {
        "p": 0.5199674960410059,
        "q": 0.0892797557587952,
        "r": 0.3907527482001989
      },
      "evidence": {
        "e1": 0.24307807476899196,
        "e2": 0.42930233428549897,
        "e3": 0.327619590945509
      },
      "trustMetrics": {
        "directTrust": 1.1969914694695725,
        "indirectTrust": 0.8395980170198776,
        "overallTrust": 0.05091473716223625
      },
      "isSybil": false
    },
    {
      "id": 24,
      "address": "0xa57a6c797298e80911b8e5655fbc8583",
      "name": "Bob",
      "group": 7,
      "subjectiveProbs": {
        "p": 0.6808826668438872,
        "q": 0.20559023111398336,
        "r": 0.11352710204212947
      },
      "evidence": {
        "e1": 0.6220008185430849,
        "e2": 0.18143934334441514,
        "e3": 0.19655983811250002
      },
      "trustMetrics": {
        "directTrust": 0.2615272225074179,
        "indirectTrust": 0.8629846231939314,
        "overallTrust": 0.028112796142533737
      },
      "isSybil": false
    },
    {
      "id": 25,
      "address": "0xf03e8f44d9f1dbbad6397449445bf8bc",
      "name": "Frank",
      "group": 4,
      "subjectiveProbs": {
        "p": 0.3121093170542347,
        "q": 0.4152166902166623,
        "r": 0.2726739927291029
      },
      "evidence": {
        "e1": 0.5074615422849532,
        "e2": 0.41466338025196753,
        "e3": 0.0778750774630793
      },
      "trustMetrics": {
        "directTrust": 1.9922863424073762,
        "indirectTrust": 0.8197156451964325,
        "overallTrust": 0.07030004969009522
      },
      "isSybil": false
    },
    {
      "id": 26,
      "address": "0x8114007c46ff685042e9eb789e814a31",
      "name": "Gina",
      "group": 0,
      "subjectiveProbs": {
        "p": 0.509003481440283,
        "q": 0.12017902337022512,
        "r": 0.37081749518949186
      },
      "evidence": {
        "e1": 0.35304202271657237,
        "e2": 0.3100442630361623,
        "e3": 0.3369137142472654
      },
      "trustMetrics": {
        "directTrust": 0.8281877248076831,
        "indirectTrust": 0.8488181106364248,
        "overallTrust": 0.0419251458861027
      },
      "isSybil": false
    },
    {
      "id": 27,
      "address": "0x0414d763c8e745811bf57b19dc318dd6",
      "name": "Henry",
      "group": 6,
      "subjectiveProbs": {
        "p": 0.4192973162143833,
        "q": 0.4257167278291655,
        "r": 0.1549859559564512
      },
      "evidence": {
        "e1": 0.7158481916033163,
        "e2": 0.25775815456783197,
        "e3": 0.02639365382885175
      },
      "trustMetrics": {
        "directTrust": 1.1347741642132767,
        "indirectTrust": 0.841153449651285,
        "overallTrust": 0.049398190346614045
      },
      "isSybil": false
    },
    {
      "id": 28,
      "address": "0xb45336ecee4b82c87e21e9afbac832fa",
      "name": "Dave",
      "group": 4,
      "subjectiveProbs": {
        "p": 0.2944798333513861,
        "q": 0.31443464159127515,
        "r": 0.39108552505733885
      },
      "evidence": {
        "e1": 0.2353596867271271,
        "e2": 0.5425388048029172,
        "e3": 0.22210150846995572
      },
      "trustMetrics": {
        "directTrust": 1.9173959400478784,
        "indirectTrust": 0.82158790525542,
        "overallTrust": 0.06847459613258247
      },
      "isSybil": false
    },
    {
      "id": 29,
      "address": "0xeebb630bf8e11073d1b18d545d7a84d2",
      "name": "Jack",
      "group": 6,
      "subjectiveProbs": {
        "p": 0.27247513658093797,
        "q": 0.20001760727538537,
        "r": 0.5275072561436767
      },
      "evidence": {
        "e1": 0.25549722906047595,
        "e2": 0.41622373941203744,
        "e3": 0.3282790315274867
      },
      "trustMetrics": {
        "directTrust": 1.0163336116987132,
        "indirectTrust": 0.8441144634641491,
        "overallTrust": 0.046511201879071554
      },
      "isSybil": false
    },
    {
      "id": 30,
      "address": "0x84d45a11bba5211f6ba05df66bb3e852",
      "name": "Frank",
      "group": 4,
      "subjectiveProbs": {
        "p": 0.46549697894515824,
        "q": 0.43806426418443184,
        "r": 0.09643875687040993
      },
      "evidence": {
        "e1": 0.2241603344488533,
        "e2": 0.13902753603792686,
        "e3": 0.6368121295132199
      },
      "trustMetrics": {
        "directTrust": 1.547158088385112,
        "indirectTrust": 0.8308438515469891,
        "overallTrust": 0.05945004849830253
      },
      "isSybil": false
    },
    {
      "id": 31,
      "address": "0xef067e0c916edd8958d062884e3220b6",
      "name": "Eve",
      "group": 0,
      "subjectiveProbs": {
        "p": 0.5927186108017904,
        "q": 0.006326847662174746,
        "r": 0.4009545415360348
      },
      "evidence": {
        "e1": 0.324405275502166,
        "e2": 0.30164150012439367,
        "e3": 0.3739532243734403
      },
      "trustMetrics": {
        "directTrust": 0.8306688046365154,
        "indirectTrust": 0.848756083640704,
        "overallTrust": 0.04198562220693049
      },
      "isSybil": false
    },
    {
      "id": 32,
      "address": "0xe89bfbf048600c78bdacdb55ec483e62",
      "name": "Ida",
      "group": 4,
      "subjectiveProbs": {
        "p": 0.2562276031172144,
        "q": 0.21217801755241875,
        "r": 0.5315943793303669
      },
      "evidence": {
        "e1": 0.34720957378869155,
        "e2": 0.32081995636808897,
        "e3": 0.3319704698432195
      },
      "trustMetrics": {
        "directTrust": 1.9381963647379665,
        "indirectTrust": 0.8210678946381677,
        "overallTrust": 0.06898160648440335
      },
      "isSybil": false
    },
    {
      "id": 33,
      "address": "0xbafe88003e36131ab1215c5e2bb8d043",
      "name": "Charlie",
      "group": 1,
      "subjectiveProbs": {
        "p": 0.6275915797250217,
        "q": 0.23297603037759565,
        "r": 0.13943238989738269
      },
      "evidence": {
        "e1": 0.9256873096690165,
        "e2": 0.006203456990885214,
        "e3": 0.06810923334009832
      },
      "trustMetrics": {
        "directTrust": 0,
        "indirectTrust": 0.869522803756617,
        "overallTrust": 0.021738070093915422
      },
      "isSybil": false
    },
    {
      "id": 34,
      "address": "0xb03cf18fa253c2d6ab66bf7cfe4d12ba",
      "name": "Bob",
      "group": 2,
      "subjectiveProbs": {
        "p": 0.10513489397817742,
        "q": 0.14577618882002139,
        "r": 0.7490889172018012
      },
      "evidence": {
        "e1": 0.32461774279010575,
        "e2": 0.248882752912361,
        "e3": 0.42649950429753325
      },
      "trustMetrics": {
        "directTrust": 1.3645122830818137,
        "indirectTrust": 0.8354099966795715,
        "overallTrust": 0.05499805699403463
      },
      "isSybil": false
    },
    {
      "id": 35,
      "address": "0xdbecfe38a1d0fb96381871736e89a227",
      "name": "Dave",
      "group": 2,
      "subjectiveProbs": {
        "p": 0.40642733669802994,
        "q": 0.36146466342568107,
        "r": 0.23210799987628897
      },
      "evidence": {
        "e1": 0.0067777432768489606,
        "e2": 0.3352869188891087,
        "e3": 0.6579353378340423
      },
      "trustMetrics": {
        "directTrust": 1.1623072107844845,
        "indirectTrust": 0.8404651234870049,
        "overallTrust": 0.05006930835678723
      },
      "isSybil": false
    },
    {
      "id": 36,
      "address": "0x842dfaee1b1dd9e2e73fa35d959deaaf",
      "name": "Gina",
      "group": 2,
      "subjectiveProbs": {
        "p": 0.2310632414495139,
        "q": 0.38612481738213306,
        "r": 0.38281194116835304
      },
      "evidence": {
        "e1": 0.24778170900310517,
        "e2": 0.1332327683494097,
        "e3": 0.6189855226474852
      },
      "trustMetrics": {
        "directTrust": 1.2965094317004415,
        "indirectTrust": 0.8371100679641058,
        "overallTrust": 0.053340487491613686
      },
      "isSybil": false
    },
    {
      "id": 37,
      "address": "0xcfcddd7e5fd1e767ea16a18a677098c7",
      "name": "Alice",
      "group": 2,
      "subjectiveProbs": {
        "p": 0.41406676545375737,
        "q": 0.129948958684653,
        "r": 0.4559842758615896
      },
      "evidence": {
        "e1": 0.11557260578313182,
        "e2": 0.8287108073266,
        "e3": 0.05571658689026819
      },
      "trustMetrics": {
        "directTrust": 0.9028072813354288,
        "indirectTrust": 0.8469526217232313,
        "overallTrust": 0.0437439975764665
      },
      "isSybil": false
    },
    {
      "id": 38,
      "address": "0xd330fe34ae8ceb82915dae7d32f4977f",
      "name": "Ida",
      "group": 6,
      "subjectiveProbs": {
        "p": 0.4664373624863062,
        "q": 0.1881252326642165,
        "r": 0.3454374048494773
      },
      "evidence": {
        "e1": 0.35583437936089135,
        "e2": 0.4304925298658798,
        "e3": 0.2136730907732288
      },
      "trustMetrics": {
        "directTrust": 1.007830728710907,
        "indirectTrust": 0.8443270355388443,
        "overallTrust": 0.04630394410624378
      },
      "isSybil": false
    },
    {
      "id": 39,
      "address": "0x213710e1a9534dbddab96f0245c703fd",
      "name": "Dave",
      "group": 0,
      "subjectiveProbs": {
        "p": 0.23052232266944067,
        "q": 0.32095984085638624,
        "r": 0.4485178364741731
      },
      "evidence": {
        "e1": 0.7539471847001971,
        "e2": 0.13503314322329554,
        "e3": 0.11101967207650738
      },
      "trustMetrics": {
        "directTrust": 0.729335514091827,
        "indirectTrust": 0.8512894159043212,
        "overallTrust": 0.0395156232499037
      },
      "isSybil": false
    }
  ],
  "links": [
    {
      "source": 0,
      "target": 23,
      "trust": 0.1798196291969441
    },
    {
      "source": 0,
      "target": 34,
      "trust": 0.21231860913137418
    },
    {
      "source": 0,
      "target": 35,
      "trust": 0.1736217764048933
    },
    {
      "source": 0,
      "target": 36,
      "trust": 0.19848389199221736
    },
    {
      "source": 0,
      "target": 37,
      "trust": 0.1303529353650341
    },
    {
      "source": 1,
      "target": 20,
      "trust": 0.20447073548985284
    },
    {
      "source": 2,
      "target": 21,
      "trust": 0.2133207169660696
    },
    {
      "source": 2,
      "target": 25,
      "trust": 0.21862770442003573
    },
    {
      "source": 2,
      "target": 28,
      "trust": 0.208692713939974
    },
    {
      "source": 2,
      "target": 30,
      "trust": 0.16278014496342455
    },
    {
      "source": 2,
      "target": 32,
      "trust": 0.21142437184921387
    },
    {
      "source": 3,
      "target": 27,
      "trust": 0.25617755036772333
    },
    {
      "source": 3,
      "target": 29,
      "trust": 0.2195357330632635
    },
    {
      "source": 3,
      "target": 38,
      "trust": 0.21713521043367015
    },
    {
      "source": 4,
      "target": 21,
      "trust": 0.20240030343050985
    },
    {
      "source": 4,
      "target": 25,
      "trust": 0.20717176642310714
    },
    {
      "source": 4,
      "target": 28,
      "trust": 0.19822937739058388
    },
    {
      "source": 4,
      "target": 30,
      "trust": 0.15634326373961718
    },
    {
      "source": 4,
      "target": 32,
      "trust": 0.20069236853544342
    },
    {
      "source": 5,
      "target": 21,
      "trust": 0.20427074238896797
    },
    {
      "source": 5,
      "target": 25,
      "trust": 0.20913186080480273
    },
    {
      "source": 5,
      "target": 28,
      "trust": 0.20002317960845273
    },
    {
      "source": 5,
      "target": 30,
      "trust": 0.15745696125999897
    },
    {
      "source": 5,
      "target": 32,
      "trust": 0.2025312302565678
    },
    {
      "source": 6,
      "target": 22,
      "trust": 0.2161014960782019
    },
    {
      "source": 7,
      "target": 21,
      "trust": 0.1725761981941859
    },
    {
      "source": 7,
      "target": 25,
      "trust": 0.17603308394454253
    },
    {
      "source": 7,
      "target": 28,
      "trust": 0.1695346638856119
    },
    {
      "source": 7,
      "target": 30,
      "trust": 0.1379306544684155
    },
    {
      "source": 7,
      "target": 32,
      "trust": 0.17133296919247934
    },
    {
      "source": 8,
      "target": 20,
      "trust": 0.1827932799879312
    },
    {
      "source": 9,
      "target": 22,
      "trust": 0.2113531510122418
    },
    {
      "source": 10,
      "target": 20,
      "trust": 0.21682136793598414
    },
    {
      "source": 11,
      "target": 21,
      "trust": 0.21802434300188048
    },
    {
      "source": 11,
      "target": 25,
      "trust": 0.2235709866040139
    },
    {
      "source": 11,
      "target": 28,
      "trust": 0.21319231062318136
    },
    {
      "source": 11,
      "target": 30,
      "trust": 0.16550476979234316
    },
    {
      "source": 11,
      "target": 32,
      "trust": 0.21604383700218532
    },
    {
      "source": 12,
      "target": 27,
      "trust": 0.20652296605354545
    },
    {
      "source": 12,
      "target": 29,
      "trust": 0.1820299672035743
    },
    {
      "source": 12,
      "target": 38,
      "trust": 0.18037650908104605
    },
    {
      "source": 13,
      "target": 24,
      "trust": 0.2615272225074179
    },
    {
      "source": 14,
      "target": 23,
      "trust": 0.18183448997683202
    },
    {
      "source": 14,
      "target": 34,
      "trust": 0.21513327818519576
    },
    {
      "source": 14,
      "target": 35,
      "trust": 0.17549941302277072
    },
    {
      "source": 14,
      "target": 36,
      "trust": 0.20094158007094745
    },
    {
      "source": 14,
      "target": 37,
      "trust": 0.13140847825344953
    },
    {
      "source": 15,
      "target": 26,
      "trust": 0.23003346101354266
    },
    {
      "source": 15,
      "target": 31,
      "trust": 0.2310425157358802
    },
    {
      "source": 15,
      "target": 39,
      "trust": 0.19347884215384184
    },
    {
      "source": 16,
      "target": 27,
      "trust": 0.22839458451687883
    },
    {
      "source": 16,
      "target": 29,
      "trust": 0.1988106362215686
    },
    {
      "source": 16,
      "target": 38,
      "trust": 0.19683992433509181
    },
    {
      "source": 17,
      "target": 21,
      "trust": 0.17538427007222926
    },
    {
      "source": 17,
      "target": 25,
      "trust": 0.17895573250190022
    },
    {
      "source": 17,
      "target": 28,
      "trust": 0.17224385048220694
    },
    {
      "source": 17,
      "target": 30,
      "trust": 0.13971858924580674
    },
    {
      "source": 17,
      "target": 32,
      "trust": 0.17410040402836147
    },
    {
      "source": 18,
      "target": 23,
      "trust": 0.15448075317990917
    },
    {
      "source": 18,
      "target": 34,
      "trust": 0.17787033595873603
    },
    {
      "source": 18,
      "target": 35,
      "trust": 0.14988422149172392
    },
    {
      "source": 18,
      "target": 36,
      "trust": 0.16805699100798133
    },
    {
      "source": 18,
      "target": 37,
      "trust": 0.11650054724420718
    },
    {
      "source": 19,
      "target": 26,
      "trust": 0.21481571000869942
    },
    {
      "source": 19,
      "target": 31,
      "trust": 0.21569541845214993
    },
    {
      "source": 19,
      "target": 39,
      "trust": 0.1825989361446165
    },
    {
      "source": 21,
      "target": 25,
      "trust": 0.20837888650878475
    },
    {
      "source": 21,
      "target": 28,
      "trust": 0.19933426005508345
    },
    {
      "source": 21,
      "target": 30,
      "trust": 0.1570297427888532
    },
    {
      "source": 21,
      "target": 32,
      "trust": 0.20182495644243606
    },
    {
      "source": 23,
      "target": 34,
      "trust": 0.20077096258609808
    },
    {
      "source": 23,
      "target": 35,
      "trust": 0.1658225366615072
    },
    {
      "source": 23,
      "target": 36,
      "trust": 0.1883562171919494
    },
    {
      "source": 23,
      "target": 37,
      "trust": 0.1259068806763326
    },
    {
      "source": 25,
      "target": 28,
      "trust": 0.203960605657591
    },
    {
      "source": 25,
      "target": 30,
      "trust": 0.1598867023699307
    },
    {
      "source": 25,
      "target": 32,
      "trust": 0.20656901317266751
    },
    {
      "source": 26,
      "target": 31,
      "trust": 0.20700584422027885
    },
    {
      "source": 26,
      "target": 39,
      "trust": 0.17633270956516225
    },
    {
      "source": 27,
      "target": 29,
      "trust": 0.2230786268121685
    },
    {
      "source": 27,
      "target": 38,
      "trust": 0.22060043646296054
    },
    {
      "source": 28,
      "target": 30,
      "trust": 0.154507511951652
    },
    {
      "source": 28,
      "target": 32,
      "trust": 0.19767746645354153
    },
    {
      "source": 29,
      "target": 38,
      "trust": 0.1928786483981383
    },
    {
      "source": 30,
      "target": 32,
      "trust": 0.15599974780507014
    },
    {
      "source": 31,
      "target": 39,
      "trust": 0.17692502622820644
    },
    {
      "source": 34,
      "target": 35,
      "trust": 0.1930756141336943
    },
    {
      "source": 34,
      "target": 36,
      "trust": 0.2243226787876566
    },
    {
      "source": 34,
      "target": 37,
      "trust": 0.14102080429905878
    },
    {
      "source": 35,
      "target": 36,
      "trust": 0.18156704311111882
    },
    {
      "source": 35,
      "target": 37,
      "trust": 0.12283660595877617
    },
    {
      "source": 36,
      "target": 37,
      "trust": 0.13478102953857043
    }
  ]
}